CHANGELOG.txt
LICENCE.txt
MANIFEST.in
README.txt
setup.py
pyPDB2/__init__.py
pyPDB2.egg-info/PKG-INFO
pyPDB2.egg-info/SOURCES.txt
pyPDB2.egg-info/dependency_links.txt
pyPDB2.egg-info/requires.txt
pyPDB2.egg-info/top_level.txt