Metadata-Version: 1.1
Name: pyPDB2
Version: 0.0.1
Summary: Dialog Boxes
Home-page: UNKNOWN
Author: Jack Boyd
Author-email: boydypug@gmail.com
License: MIT
Keywords: Dialog,Box
Platform: UNKNOWN
Classifier: Development Status :: 5 - Production/Stable
Classifier: Intended Audience :: Education
Classifier: Operating System :: Microsoft :: Windows :: Windows 10
Classifier: License :: OSI Approved :: MIT License
Classifier: Programming Language :: Python :: 3
